cpu.v
module cpu(
    input       clk,
    input       reset
);

// machine variables use for the runtime
// def section

// ============== cpu mangment ==============
reg  [7:0]      memory                  [0:64000];  // the memory
reg  [31:0]     pc;                                 // the program counter
reg  [31:0]     sp;                                 // the stack pointer
// ============== registers categories ==============
reg  [7:0]      reg8                    [0:15];     // registers8
reg  [15:0]     reg16                   [0:15];     // registers16
reg  [31:0]     reg32                   [0:15];     // registers32
// ============== modes ==============
reg  [7:0]      ir;                                 // current opcode instruction
reg  [7:0]      opcode;                             // current opcode
reg  [7:0]      mode;                               // mode of the operation
reg  [7:0]      operationModes;                     // operation mode
wire [3:0]      opModH;                             // operation mode high
wire [3:0]      opModL;                             // operation mode low
// ============== general registers ==============
reg  [31:0]     currentPtrAddrs;                    // register of the current uint8_t* ptr
wire [7:0]      PXB1 = currentPtrAddrs  [31:24];    // byte 1 of PX
wire [7:0]      PXB2 = currentPtrAddrs  [23:16];    // byte 2 of PX
wire [7:0]      PXB3 = currentPtrAddrs  [15:8];     // byte 3 of PX
wire [7:0]      PXB4 = currentPtrAddrs  [7:0];      // byte 4 of PX
reg  [7:0]      OprOperator;                        // operator operation
reg  [7:0]      OprOperationBytes;                  // operation bytes length
reg  [7:0]      valueRegister;                      // DX = *(uint8_t*)PX
reg  [7:0]      op_id;                              // operation id
reg  [31:0]     a, b, result;                       // result
// ============== temporaly ==============
assign          opModH = operationModes[7:4];       // operation mode high byte
assign          opModL  = operationModes[3:0];      // operation mode low byte
`define         STR_INM  "INM     "                 // operation mode
`define         STR_REG  "REGISTER"                 // register mode
`define         STR_STK  "STACK   "                 // stack mode
`define         STR_UNK  "????????"                 // unknown mode
integer i;

// ============== function for debug ==============
// | the function for convert operation modes to  |
// | human readable words for identific the opera-|
// | tions                                        |
// |                                              |
// | #DEBUG #CASTING #HUMANREADABLE               |
// ------------------------------------------------
function [63:0] castToDebug; input [3:0] modeOpr; begin 
    case (modeOpr)
        4'h0: castToDebug = `STR_INM;               // str inm
        4'h1: castToDebug = `STR_REG;               // str reg
        4'h2: castToDebug = `STR_STK;               // str stack
        default: castToDebug = `STR_UNK;            // str unknown
    endcase 
end endfunction

// ============== function for inms  ==============
// | read a inmediate in the text of the program  |
// |                                              |
// | #NONDEBUG #INM #FUNCTION                     |
// ------------------------------------------------
function [31:0] readINM; input [7:0] bytesLen; input [31:0] baseAddr; begin
    case (bytesLen)
        1: readINM = memory[baseAddr];
        2: readINM = {memory[baseAddr],memory[baseAddr + 1]};
        4: readINM = {memory[baseAddr],memory[baseAddr + 1],memory[baseAddr + 2],memory[baseAddr + 3]
        };
        default: readINM = 0;
    endcase
end endfunction

// ============== function for opers ==============
// | A instant function for the operations regs   |
// | , inms, stack and other modes                |
// |                                              |
// | #FASTER #STARTER                             |
// ------------------------------------------------
function [31:0] operateInstant; input [3:0] modeOpr; input [7:0] bytesLen; begin
    case (modeOpr)
        4'h0: begin
            operateInstant = readINM(bytesLen, pc);
            pc = pc + bytesLen;
        end
        4'h1: begin
            a = memory[pc];
            pc = pc + 1;

            case (a)
                0: operateInstant = result;
                1: operateInstant = valueRegister;
                2: operateInstant = currentPtrAddrs;
                default: operateInstant = 0;
            endcase
        end
        4'h2: begin
            operateInstant = readINM(bytesLen, sp);
            sp = sp + bytesLen;
        end
        default: begin while (1); end
    endcase
end endfunction

// ============== function for clock ==============
// | This functions keeps on the machine for make |
// | it makes things                              |
// |                                              |
// | #LOOP #NONDEBUG #DEBUG                       |
// ------------------------------------------------
always @(posedge clk) begin
    // reset signal power on/restart computer
    if (reset) begin
        pc = 0;
        sp = 63000;
        ir = 0;
    // tick of click
    end else begin
        // fetch instruction
        ir = memory[pc];                           // current instruction
        pc = pc + 1;                               // increment program counter

        case (ir)
            // LPX = Load Pointer eXpretion
            8'h01: begin
                // fetch mode
                mode = memory[pc];
                pc = pc + 1;
                // mode of operation
                case (mode)
                    // from inmediate
                    8'h20: begin
                        currentPtrAddrs = {
                            memory      [pc],       // blk1
                            memory      [pc+1],     // blk2
                            memory      [pc+2],     // blk3
                            memory      [pc+3]      // blk4
                        };
                        pc = pc + 4;                // increment pc
                        $display("INM32      LPX 0x%x", currentPtrAddrs);
                        pc = pc + 1;                // increment pc         
                    end
                    // from stack
                    8'h1A: begin
                        $display("STACK32    LPX");
                        currentPtrAddrs = {
                            memory      [sp],       // blk1
                            memory      [sp+1],     // blk2
                            memory      [sp+2],     // blk3
                            memory      [sp+3]      // blk4
                        };
                         sp = sp + 4;               // increment pc 
                    end
                endcase
            end
            // LDX = Load From Memory To Data RegiXter (Data Register = valueRegister beta name)
            8'h02: begin
                $display("REGISTER8  LDX");
                valueRegister = memory[currentPtrAddrs];
            end
            // PUS = Push Unity or regiSter
            8'h03: begin
                mode = memory[pc];
                OprOperationBytes = memory[pc + 1];
                pc = pc + 2;

                a = operateInstant(mode[7:4],OprOperationBytes);

                $display("ANONYMUS   PUS %0d", a);

                for (i = 0; i < OprOperationBytes; i = i + 1) begin
                    sp = sp - 1;
                    memory[sp] = a >> (8*i);
                end
            end
            // OPR = Operation Propurse with Result
            8'h04: begin
                // fetch mode
                OprOperator = memory[pc];           // operator
                OprOperationBytes = memory[pc + 1]; // operation bytes len
                operationModes = memory[pc + 2];    // operation mode
                pc = pc + 3;                        // increment pc

                $write("ANONYMUS");
                if ((OprOperationBytes * 8) < 10)
                    $write("%0d ", OprOperationBytes * 8);
                else
                    $write("%0d", OprOperationBytes * 8);
                $write(" OPR %0d ", OprOperator);

                $write("%s ", castToDebug(operationModes[7:4]));
                $write("%s\n", castToDebug(operationModes[3:0]));

                a = operateInstant(operationModes[7:4],OprOperationBytes);
                b = operateInstant(operationModes[3:0],OprOperationBytes);

                case (OprOperator) 
                    8'h01: result = a + b;
                    8'h02: result = a - b;
                    8'h03: result = a * b;
                    8'h04: result = a / b;
                endcase

            end

        endcase
    end
end

endmodule

tb.v
module tb;

reg clk = 0;
reg reset = 1;

always #1 clk = ~clk;

integer i;

cpu uut(
    .clk(clk),
    .reset(reset)
);

initial begin
    
    $readmemh("program.hex", uut.memory);
    $display("pulsar5024XM_x32 chip debug");
    //$dumpfile("wave.vcd");
    //$dumpvars(0, tb);
    #10 reset = 0;
    //#40 $finish;
end

endmodule

wave.vcd
$date
	Sun May 03 16:24:10 2026
$end
$version
	Icarus Verilog
$end
$timescale
	1s
$end
$scope module tb $end
$var reg 1 ! clk $end
$var reg 1 " reset $end
$scope module uut $end
$var wire 1 ! clk $end
$var wire 1 " reset $end
$var wire 4 # opModL [3:0] $end
$var wire 4 $ opModH [3:0] $end
$var wire 8 % PXB4 [7:0] $end
$var wire 8 & PXB3 [7:0] $end
$var wire 8 ' PXB2 [7:0] $end
$var wire 8 ( PXB1 [7:0] $end
$var reg 8 ) OprOperationBytes [7:0] $end
$var reg 8 * OprOperator [7:0] $end
$var reg 32 + a [31:0] $end
$var reg 32 , b [31:0] $end
$var reg 32 - currentPtrAddrs [31:0] $end
$var reg 8 . ir [7:0] $end
$var reg 8 / mode [7:0] $end
$var reg 8 0 operationModes [7:0] $end
$var reg 32 1 pc [31:0] $end
$var reg 32 2 result [31:0] $end
$var reg 32 3 sp [31:0] $end
$var reg 8 4 valueRegister [7:0] $end
$var integer 32 5 i [31:0] $end
$scope function castToDebug $end
$var reg 4 6 modeOpr [3:0] $end
$upscope $end
$scope function operateInstant $end
$var reg 8 7 bytesLen [7:0] $end
$var reg 4 8 modeOpr [3:0] $end
$upscope $end
$scope function readINM $end
$var reg 32 9 baseAddr [31:0] $end
$var reg 8 : bytesLen [7:0] $end
$upscope $end
$upscope $end
$upscope $end
$enddefinitions $end
#0
$dumpvars
bx :
bx 9
bx 8
bx 7
bx 6
bx 5
bx 4
bx 3
bx 2
bx 1
bx 0
bx /
bx .
bx -
bx ,
bx +
bx *
bx )
bx (
bx '
bx &
bx %
bx $
bx #
1"
0!
$end
#1
b0 .
b1111011000011000 3
b0 1
1!
#2
0!
#3
1!
#4
0!
#5
1!
#6
0!
#7
1!
#8
0!
#9
1!
#10
0!
0"
#11
b1111011000010110 3
b10 5
b100000000 +
b10 :
b11 9
b0 8
b10 7
b10 )
b0 /
b101 1
b11 .
1!
#12
0!
#13
b1111011000010100 3
b10 5
b1000 9
b1010 1
1!
#14
0!
#15
b10 $
b10 #
b1000000000 2
b100000000 ,
b1111011000011000 3
b1111011000010110 9
b10 8
b10 6
b100010 0
b1 *
b1110 1
b100 .
1!
#16
0!
#17
b1111 1
bx .
1!
#18
0!
#19
b10000 1
1!
#20
0!
#21
b10001 1
1!
#22
0!
#23
b10010 1
1!
#24
0!
#25
b10011 1
1!
#26
0!
#27
b10100 1
1!
#28
0!
#29
b10101 1
1!
#30
0!
#31
b10110 1
1!
#32
0!
#33
b10111 1
1!
#34
0!
#35
b11000 1
1!
#36
0!
#37
b11001 1
1!
#38
0!
#39
b11010 1
1!
#40
0!
#41
b11011 1
1!
#42
0!
#43
b11100 1
1!
#44
0!
#45
b11101 1
1!
#46
0!
#47
b11110 1
1!
#48
0!
#49
b11111 1
1!
